partial_tagger/__init__.py
partial_tagger/crf/__init__.py
partial_tagger/crf/functional.py
partial_tagger/crf/nn.py
partial_tagger/decoders/__init__.py
partial_tagger/decoders/base.py
partial_tagger/decoders/viterbi.py
partial_tagger/embedders.py
partial_tagger/encoders/__init__.py
partial_tagger/encoders/base.py
partial_tagger/encoders/linear.py
partial_tagger/tagger.py
partial_tagger-0.6.1.dist-info/LICENSE
partial_tagger-0.6.1.dist-info/WHEEL
partial_tagger-0.6.1.dist-info/METADATA
partial_tagger-0.6.1.dist-info/RECORD
