Metadata-Version: 2.1
Name: partial-tagger
Version: 0.6.1
Summary: Sequence Tagger for Partially Annotated Dataset in PyTorch
Home-page: https://github.com/tech-sketch/partial-tagger
License: MIT
Author: yasufumi
Author-email: yasufumi.taniguchi@gmail.com
Requires-Python: >=3.8,<4.0
Classifier: License :: OSI Approved :: MIT License
Classifier: Programming Language :: Python
Classifier: Programming Language :: Python :: 3
Classifier: Programming Language :: Python :: 3.10
Classifier: Programming Language :: Python :: 3.8
Classifier: Programming Language :: Python :: 3.9
Requires-Dist: torch (>=1.11.0,<2.0.0)
Project-URL: Repository, https://github.com/tech-sketch/partial-tagger
